<?xml version="1.0" encoding="UTF-8"?>
<PANEL>

	<PANEL_ID>D1_CG_FGM_BGSE_TOT_CAA</PANEL_ID>

	<INFO>D1 FGM</INFO>

	<SUBPANEL>
		<ORDER>1</ORDER>

		<PLOT>

			<PROCESSING>
				<ORDER>1</ORDER>
				<NAME>TIME_AVERAGE</NAME>
                		<VALUE>0</VALUE>
				<ARGUMENT>
					<PARAMID>Time_tags__D1_CP_FGM_SPIN</PARAMID>
                    			<DATASETID>D1_CP_FGM_SPIN</DATASETID>
					<ALIAS>INPUT_1</ALIAS>
                    			<TYPE>INPUT</TYPE>
				</ARGUMENT>
  				<ARGUMENT>
					<PARAMID>Time_tags_jul__D1_CP_FGM_SPIN</PARAMID>
					<ALIAS>OUTPUT_1</ALIAS>
                    			<TYPE>OUTPUT</TYPE>
				</ARGUMENT>
                		<ARGUMENT>
					<PARAMID>Time_tags_av__D1_CP_FGM_SPIN</PARAMID>
					<ALIAS>OUTPUT_2</ALIAS>
                    			<TYPE>OUTPUT</TYPE>
				</ARGUMENT>
            		</PROCESSING>


                        <PROCESSING>
                                <ORDER>2</ORDER>
                                <NAME>TOTAL_POWER</NAME>
                                <ARGUMENT>
                                        <PARAMID>B_vec_xyz_gse__D1_CP_FGM_SPIN</PARAMID>
                                        <DATASETID>D1_CP_FGM_SPIN</DATASETID>
                                        <ALIAS>INPUT_1</ALIAS>
                                        <TYPE>INPUT</TYPE>
                                </ARGUMENT>
                                <ARGUMENT>
                                        <PARAMID>B_vec_xyz_gse_totp__D1_CP_FGM_SPIN</PARAMID>
                                        <ALIAS>OUTPUT_1</ALIAS>
                                        <TYPE>OUTPUT</TYPE>
                                </ARGUMENT>
                        </PROCESSING>

            		<PROCESSING>
                   		<ORDER>3</ORDER>
                   		<NAME>DATA_AVERAGE</NAME>
                   		<VALUE>180</VALUE>
                   		<ARGUMENT>
                       			<PARAMID>B_vec_xyz_gse_totp__D1_CP_FGM_SPIN</PARAMID>
                       			<ALIAS>INPUT_1</ALIAS>
                       			<TYPE>INPUT</TYPE>
                   		</ARGUMENT>
                   		<ARGUMENT>
                       			<PARAMID>Time_tags_jul__D1_CP_FGM_SPIN</PARAMID>
                       			<ALIAS>INPUT_2</ALIAS>
                       			<TYPE>INPUT</TYPE>
                   		</ARGUMENT>
                   		<ARGUMENT>
                       			<PARAMID>Time_tags_av__D1_CP_FGM_SPIN</PARAMID>
                       			<ALIAS>INPUT_3</ALIAS>
                       			<TYPE>INPUT</TYPE>
                   		</ARGUMENT>
                   		<ARGUMENT>
                       			<PARAMID>B_vec_xyz_gse_totp_av__D1_CP_FGM_SPIN</PARAMID>
                       			<ALIAS>OUTPUT_1</ALIAS>
                       			<TYPE>OUTPUT</TYPE>
                 		</ARGUMENT>
            		</PROCESSING>

			<PLOT_DATA>
				<PARAMID>Time_tags_av__D1_CP_FGM_SPIN</PARAMID>
				<TYPE>X</TYPE>
			</PLOT_DATA>
            		<PLOT_DATA>
                		<PARAMID>B_vec_xyz_gse_totp_av__D1_CP_FGM_SPIN</PARAMID>
                		<TYPE>Y</TYPE>
            		</PLOT_DATA>

            		<LINE>
                		<COLOR>black</COLOR>
                		<NAME>D1</NAME>
                                <LEGEND>0</LEGEND>
            		</LINE>


			<ORDER>1</ORDER>

			<AXIS>
				<TYPE>YAXIS</TYPE>
				<LOG>1</LOG>
				<UNIT>nT</UNIT>
				<LABEL>|B|</LABEL>
			</AXIS>

			<PLOT_TYPE>line</PLOT_TYPE>

		</PLOT>
	</SUBPANEL>

</PANEL>


